MANIFEST.in
README.md
setup.py
spacy_cld/__init__.py
spacy_cld/about.py
spacy_cld/spacy_cld.py
spacy_cld.egg-info/PKG-INFO
spacy_cld.egg-info/SOURCES.txt
spacy_cld.egg-info/dependency_links.txt
spacy_cld.egg-info/not-zip-safe
spacy_cld.egg-info/requires.txt
spacy_cld.egg-info/top_level.txt
tests/__init__.py
tests/test_language_detector.py