Metadata-Version: 1.0
Name: spacy-cld
Version: 0.1.0
Summary: spaCy pipeline component for guessing the language of Doc and Span objects.
Home-page: https://github.com/nickdavidhaynes/spacy-cld
Author: Nick Haynes
Author-email: nickdavidhaynes@gmail.com
License: MIT
Platform: UNKNOWN
